oauthgenerator/__init__.py
oauthgenerator-1.0.0.dist-info/METADATA
oauthgenerator-1.0.0.dist-info/WHEEL
oauthgenerator-1.0.0.dist-info/top_level.txt
oauthgenerator-1.0.0.dist-info/RECORD
