Metadata-Version: 2.1
Name: oauthgenerator
Version: 1.0.0
Summary: oauth
Home-page: UNKNOWN
Author: ЕntchenBuilds
Author-email: ЕntchenBuilds@gmail.com
License: UNKNOWN
Keywords: python
Platform: UNKNOWN
Classifier: Operating System :: Microsoft :: Windows
